README.md
setup.py
unicase/__init__.py
unicase/cli.py
unicase/utils.py
unicase/template/bvt_task.html
unicase/template/case.xlsm
unicase/template/case.xlsm(20210712).bak
unicase/template/case.xlsm.bak
unicase_cli.egg-info/PKG-INFO
unicase_cli.egg-info/SOURCES.txt
unicase_cli.egg-info/dependency_links.txt
unicase_cli.egg-info/entry_points.txt
unicase_cli.egg-info/requires.txt
unicase_cli.egg-info/top_level.txt