Metadata-Version: 2.1
Name: unicase-cli
Version: 1.2.3
Summary: manage Excel cases
Home-page: https://github.com/mocobk/unicase
Author: mocobk
Author-email: mailmzb@qq.com
License: UNKNOWN
Keywords: unicase-cli,unicase,case,excel
Platform: UNKNOWN
Classifier: Programming Language :: Python :: 3 :: Only
Classifier: Programming Language :: Python :: 3.6
Classifier: Programming Language :: Python :: 3.7
Classifier: Programming Language :: Python :: 3.8
Classifier: License :: OSI Approved :: MIT License
Classifier: Operating System :: OS Independent
